{"stats":{"minecraft:custom":{"minecraft:talked_to_villager":1,"minecraft:time_since_rest":514,"minecraft:walk_one_cm":2741,"minecraft:leave_game":2,"minecraft:damage_taken":190,"minecraft:play_time":3383,"minecraft:damage_dealt":10,"minecraft:jump":135,"minecraft:time_since_death":3383,"minecraft:sprint_one_cm":19768,"minecraft:sleep_in_bed":1,"minecraft:fall_one_cm":8362,"minecraft:total_world_time":3383,"minecraft:fly_one_cm":27470,"minecraft:crouch_one_cm":1291,"minecraft:sneak_time":424,"minecraft:climb_one_cm":1158},"minecraft:used":{"minecraft:oak_planks":20},"minecraft:picked_up":{"minecraft:string":1,"minecraft:oak_log":5,"minecraft:oak_planks":20},"minecraft:mined":{"minecraft:oak_leaves":2}},"DataVersion":4440}